sengkalancli/__init__.py
sengkalancli/__main__.py
sengkalancli/sengkalancli.py
sengkalancli-0.1.dist-info/LICENCE
sengkalancli-0.1.dist-info/METADATA
sengkalancli-0.1.dist-info/WHEEL
sengkalancli-0.1.dist-info/entry_points.txt
sengkalancli-0.1.dist-info/top_level.txt
sengkalancli-0.1.dist-info/RECORD
